pymathisrtelib/__init__.py
pymathisrtelib/functions.py
tests/__init__.py
tests/test_get_nni.py
tests/test_get_results.py
tests/test_get_token.py
pymathisrte-0.2.0.dist-info/METADATA
pymathisrte-0.2.0.dist-info/WHEEL
pymathisrte-0.2.0.dist-info/top_level.txt
pymathisrte-0.2.0.dist-info/RECORD
